rambench.abi3.so
rambenchmark-1.3.dist-info/LICENSE
rambenchmark-1.3.dist-info/RECORD
rambenchmark-1.3.dist-info/METADATA
rambenchmark-1.3.dist-info/entry_points.txt
rambenchmark-1.3.dist-info/top_level.txt
rambenchmark-1.3.dist-info/WHEEL
rambenchmark.libs/libgomp-3300acd3.so.1.0.0
rambenchmark/__main__.py
rambenchmark/__init__.py
rambenchmark/rambenchmark.py
