Metadata-Version: 2.1
Name: rambenchmark
Version: 1.3
Summary: RAM memory benchmark.
Home-page: https://github.com/rsusik/rambenchmark
Author: Robert Susik
Author-email: robert.susik@gmail.com
License: UNKNOWN
Platform: UNKNOWN
Classifier: Intended Audience :: Developers 
Classifier: Intended Audience :: Science/Research
Classifier: Environment :: Console
Classifier: License :: OSI Approved :: MIT License
Classifier: Programming Language :: Python
Classifier: Programming Language :: Python :: 3.7
Classifier: Programming Language :: C++
Classifier: Topic :: System :: Benchmark
Classifier: Topic :: System :: Hardware
Classifier: Operating System :: POSIX :: Linux
Provides-Extra: test
Requires-Dist: pytest ; extra == 'test'
